inverted_index_search/__init__.py
inverted_index_search/keyword_search.py
inverted_index_search-1.3.4.dist-info/METADATA
inverted_index_search-1.3.4.dist-info/WHEEL
inverted_index_search-1.3.4.dist-info/licenses/LICENSE
inverted_index_search-1.3.4.dist-info/RECORD
