Metadata-Version: 2.1
Name: inverted_index_search
Version: 1.3.4
Summary: A module for creating ngrams and searching multiple phrases using inverted index searching in a document
Project-URL: Homepage, https://github.com/Affanmir/Inverted-Index-search
Project-URL: Bug Tracker, https://github.com/Affanmir/Inverted-Index-search
Author-email: Affan Mir <affanmir95@gmail.com>
License-File: LICENSE
Classifier: License :: OSI Approved :: MIT License
Classifier: Operating System :: OS Independent
Classifier: Programming Language :: Python :: 3
Requires-Python: >=3.7
Requires-Dist: nltk
